docship/__init__.py
docship/__main__.py
docship/exceptions.py
docship/utils.py
docship-0.0.1.dist-info/licenses/LICENSE
docship-0.0.1.dist-info/METADATA
docship-0.0.1.dist-info/WHEEL
docship-0.0.1.dist-info/entry_points.txt
docship-0.0.1.dist-info/top_level.txt
docship-0.0.1.dist-info/RECORD
