Metadata-Version: 2.4
Name: docship
Version: 0.0.1
Summary: A tool to deploy fosscu services
Author-email: Kanishk Pachauri <itskanishkp.py@gmail.com>
License-Expression: MIT
Project-URL: Homepage, https://github.com/foSS-Community/docship
Keywords: docship,fosscu,commandline
Classifier: Intended Audience :: Developers
Classifier: Programming Language :: Python
Classifier: Programming Language :: Python :: 3
Classifier: Programming Language :: Python :: 3.9
Classifier: Programming Language :: Python :: 3.10
Classifier: Programming Language :: Python :: 3.11
Classifier: Programming Language :: Python :: 3.12
Classifier: Programming Language :: Python :: 3.13
Requires-Python: >=3.9
License-File: LICENSE
Dynamic: license-file
